{"schema":{"fields":[{"name":"index","type":"integer"},{"name":"year","type":"integer"},{"name":"precip","type":"number"},{"name":"10_year_rolling_avg","type":"number"}],"pandas_version":"1.4.0"},"data":[{"index":0,"year":1980,"precip":213.5632,"10_year_rolling_avg":null},{"index":1,"year":1981,"precip":178.4096,"10_year_rolling_avg":null},{"index":2,"year":1982,"precip":425.7294,"10_year_rolling_avg":null},{"index":3,"year":1983,"precip":256.1844,"10_year_rolling_avg":null},{"index":4,"year":1984,"precip":276.1742,"10_year_rolling_avg":null},{"index":5,"year":1985,"precip":312.0644,"10_year_rolling_avg":null},{"index":6,"year":1986,"precip":297.4848,"10_year_rolling_avg":null},{"index":7,"year":1987,"precip":257.9878,"10_year_rolling_avg":null},{"index":8,"year":1988,"precip":243.5098,"10_year_rolling_avg":null},{"index":9,"year":1989,"precip":265.7602,"10_year_rolling_avg":272.6868},{"index":10,"year":1990,"precip":237.2614,"10_year_rolling_avg":275.0566},{"index":11,"year":1991,"precip":264.1346,"10_year_rolling_avg":283.6291},{"index":12,"year":1992,"precip":309.8038,"10_year_rolling_avg":272.0365},{"index":13,"year":1993,"precip":383.4892,"10_year_rolling_avg":284.767},{"index":14,"year":1994,"precip":366.2426,"10_year_rolling_avg":293.7739},{"index":15,"year":1995,"precip":328.5744,"10_year_rolling_avg":295.4249},{"index":16,"year":1996,"precip":196.2404,"10_year_rolling_avg":285.3004},{"index":17,"year":1997,"precip":317.4238,"10_year_rolling_avg":291.244},{"index":18,"year":1998,"precip":349.3262,"10_year_rolling_avg":301.8257},{"index":19,"year":1999,"precip":203.2508,"10_year_rolling_avg":295.5747},{"index":20,"year":2000,"precip":877.9764,"10_year_rolling_avg":359.6462},{"index":21,"year":2001,"precip":746.5568,"10_year_rolling_avg":407.8884},{"index":22,"year":2002,"precip":790.3718,"10_year_rolling_avg":455.9452},{"index":23,"year":2003,"precip":523.5956,"10_year_rolling_avg":469.9559},{"index":24,"year":2004,"precip":673.1,"10_year_rolling_avg":500.6416},{"index":25,"year":2005,"precip":482.5746,"10_year_rolling_avg":516.0416},{"index":26,"year":2006,"precip":646.0744,"10_year_rolling_avg":561.025},{"index":27,"year":2007,"precip":797.6362,"10_year_rolling_avg":609.0463},{"index":28,"year":2008,"precip":1083.31,"10_year_rolling_avg":682.4447},{"index":29,"year":2009,"precip":655.6756,"10_year_rolling_avg":727.6871},{"index":30,"year":2010,"precip":632.2822,"10_year_rolling_avg":703.1177},{"index":31,"year":2011,"precip":468.8332,"10_year_rolling_avg":675.3454},{"index":32,"year":2012,"precip":877.7224,"10_year_rolling_avg":684.0804},{"index":33,"year":2013,"precip":631.5964,"10_year_rolling_avg":694.8805},{"index":34,"year":2014,"precip":1405.89,"10_year_rolling_avg":768.1595},{"index":35,"year":2015,"precip":722.8332,"10_year_rolling_avg":792.1854},{"index":36,"year":2016,"precip":661.1112,"10_year_rolling_avg":793.689},{"index":37,"year":2017,"precip":749.3254,"10_year_rolling_avg":788.858},{"index":38,"year":2018,"precip":1072.9976,"10_year_rolling_avg":787.8267},{"index":39,"year":2019,"precip":773.9634,"10_year_rolling_avg":799.6555},{"index":40,"year":2020,"precip":746.3028,"10_year_rolling_avg":811.0576},{"index":41,"year":2021,"precip":592.582,"10_year_rolling_avg":823.4324},{"index":42,"year":2022,"precip":563.8546,"10_year_rolling_avg":792.0457},{"index":43,"year":2023,"precip":819.0992,"10_year_rolling_avg":810.7959},{"index":10,"year":2024,"precip":848.6133892789,"10_year_rolling_avg":755.0683},{"index":11,"year":2025,"precip":655.2246264322,"10_year_rolling_avg":748.3074},{"index":12,"year":2026,"precip":742.3686079803,"10_year_rolling_avg":756.4332},{"index":13,"year":2027,"precip":725.3547740211,"10_year_rolling_avg":754.0361},{"index":14,"year":2028,"precip":721.7082066922,"10_year_rolling_avg":718.9072},{"index":15,"year":2029,"precip":853.1252924481,"10_year_rolling_avg":726.8233},{"index":16,"year":2030,"precip":1192.6780758456,"10_year_rolling_avg":771.4609},{"index":17,"year":2031,"precip":961.6533492281,"10_year_rolling_avg":808.368},{"index":18,"year":2032,"precip":749.4990298042,"10_year_rolling_avg":826.9325},{"index":19,"year":2033,"precip":801.7741202534,"10_year_rolling_avg":825.1999},{"index":20,"year":2034,"precip":696.277539364,"10_year_rolling_avg":809.9664},{"index":21,"year":2035,"precip":885.8568395048,"10_year_rolling_avg":833.0296},{"index":22,"year":2036,"precip":895.7742603023,"10_year_rolling_avg":848.3701},{"index":23,"year":2037,"precip":910.8720548794,"10_year_rolling_avg":866.9219},{"index":24,"year":2038,"precip":660.9951630963,"10_year_rolling_avg":860.8506},{"index":25,"year":2039,"precip":669.0848855401,"10_year_rolling_avg":842.4465},{"index":26,"year":2040,"precip":829.4017514952,"10_year_rolling_avg":806.1189},{"index":27,"year":2041,"precip":718.1003106885,"10_year_rolling_avg":781.7636},{"index":28,"year":2042,"precip":890.6859734489,"10_year_rolling_avg":795.8823},{"index":29,"year":2043,"precip":747.8879090678,"10_year_rolling_avg":790.4937},{"index":30,"year":2044,"precip":568.1756142952,"10_year_rolling_avg":777.6835},{"index":31,"year":2045,"precip":624.5733073619,"10_year_rolling_avg":751.5551},{"index":32,"year":2046,"precip":795.6340963614,"10_year_rolling_avg":741.5411},{"index":33,"year":2047,"precip":727.4515693826,"10_year_rolling_avg":723.1991},{"index":34,"year":2048,"precip":655.7836005345,"10_year_rolling_avg":722.6779},{"index":35,"year":2049,"precip":811.7669142474,"10_year_rolling_avg":736.9461},{"index":36,"year":2050,"precip":847.5168505233,"10_year_rolling_avg":738.7576},{"index":37,"year":2051,"precip":718.4514305912,"10_year_rolling_avg":738.7927},{"index":38,"year":2052,"precip":702.4199161651,"10_year_rolling_avg":719.9661},{"index":39,"year":2053,"precip":865.0531159043,"10_year_rolling_avg":731.6826},{"index":40,"year":2054,"precip":835.0075573422,"10_year_rolling_avg":758.3658},{"index":41,"year":2055,"precip":810.3132281994,"10_year_rolling_avg":776.9398},{"index":42,"year":2056,"precip":658.4567046712,"10_year_rolling_avg":763.2221},{"index":43,"year":2057,"precip":925.5141223427,"10_year_rolling_avg":783.0283},{"index":44,"year":2058,"precip":757.9007347129,"10_year_rolling_avg":793.2401},{"index":45,"year":2059,"precip":654.1648130323,"10_year_rolling_avg":777.4798},{"index":46,"year":2060,"precip":623.7735076226,"10_year_rolling_avg":755.1055},{"index":47,"year":2061,"precip":735.1109331648,"10_year_rolling_avg":756.7715},{"index":48,"year":2062,"precip":907.5524401228,"10_year_rolling_avg":777.2847},{"index":49,"year":2063,"precip":743.7938811501,"10_year_rolling_avg":765.1588},{"index":50,"year":2064,"precip":632.3244612023,"10_year_rolling_avg":744.8905},{"index":51,"year":2065,"precip":705.0107667595,"10_year_rolling_avg":734.3602},{"index":52,"year":2066,"precip":798.5964481155,"10_year_rolling_avg":748.3742},{"index":53,"year":2067,"precip":798.5995593155,"10_year_rolling_avg":735.6828},{"index":54,"year":2068,"precip":579.733384076,"10_year_rolling_avg":717.866},{"index":55,"year":2069,"precip":682.4219402506,"10_year_rolling_avg":720.6917},{"index":56,"year":2070,"precip":729.6491519922,"10_year_rolling_avg":731.2793},{"index":57,"year":2071,"precip":783.7381947708,"10_year_rolling_avg":736.142},{"index":58,"year":2072,"precip":690.6434545651,"10_year_rolling_avg":714.4511},{"index":59,"year":2073,"precip":864.0962541109,"10_year_rolling_avg":726.4814},{"index":60,"year":2074,"precip":787.1073801305,"10_year_rolling_avg":741.9597},{"index":61,"year":2075,"precip":666.1959149118,"10_year_rolling_avg":738.0782},{"index":62,"year":2076,"precip":781.9387777849,"10_year_rolling_avg":736.4124},{"index":63,"year":2077,"precip":746.8767231367,"10_year_rolling_avg":731.2401},{"index":64,"year":2078,"precip":810.6405008075,"10_year_rolling_avg":754.3308},{"index":65,"year":2079,"precip":568.4482141983,"10_year_rolling_avg":742.9335},{"index":66,"year":2080,"precip":771.9205727358,"10_year_rolling_avg":747.1606}]}